[
    {
        "id": "evt_1",
        "client_id": "cli_1",
        "client_name": "Samantha Miller",
        "venue_address": "St. Regis Ballroom, SF",
        "start_date": "2026-07-10",
        "end_date": "2026-07-12",
        "status": "Confirmed",
        "design_layout_url": "/static/seed_layout_1.jpg",
        "items_booked": "{\"inv_1\": 20, \"inv_3\": 6, \"inv_4\": 1, \"inv_5\": 1, \"inv_6\": 80}",
        "total_invoice_amount": 1170.0,
        "amount_paid": 600.0,
        "remaining_balance": 570.0,
        "crew_assignments": "[{\"worker_id\": \"usr_labor_1\", \"name\": \"Marcus Chen\", \"pay_rate\": 150.0, \"paid\": false}, {\"worker_id\": \"usr_labor_2\", \"name\": \"David Miller\", \"pay_rate\": 150.0, \"paid\": true}]",
        "max_workforce_capacity": 4,
        "notes": "Ensure drapery structures are reinforced. Uplights should match client theme color (rose gold)."
    },
    {
        "client_id": "cli_25afecf4",
        "client_name": "Alice Cooper",
        "venue_address": "San Jose Hall A",
        "start_date": "2026-08-01",
        "end_date": "2026-08-03",
        "status": "Completed",
        "design_layout_url": "",
        "items_booked": "{\"inv_7fbdc4a0\": 3}",
        "total_invoice_amount": 1080.0,
        "amount_paid": 1080.0,
        "remaining_balance": 0.0,
        "crew_assignments": "[{\"worker_id\": \"usr_labor_1\", \"name\": \"Marcus Chen\", \"pay_rate\": 150.0, \"paid\": false}]",
        "max_workforce_capacity": 4,
        "notes": "Testing auto receipt calculations",
        "id": "evt_a14da118"
    },
    {
        "client_id": "cli_25afecf4",
        "client_name": "Alice Cooper",
        "venue_address": "San Jose Hall A",
        "start_date": "2026-08-02",
        "end_date": "2026-08-04",
        "status": "Confirmed",
        "design_layout_url": "",
        "items_booked": "{\"inv_7fbdc4a0\": 3}",
        "total_invoice_amount": 1080.0,
        "amount_paid": 0.0,
        "remaining_balance": 1080.0,
        "crew_assignments": "[{\"worker_id\": \"usr_labor_1\", \"name\": \"Marcus Chen\", \"pay_rate\": 150.0, \"paid\": false}]",
        "max_workforce_capacity": 4,
        "notes": "Testing auto receipt calculations",
        "id": "evt_a98f7705"
    },
    {
        "client_id": "cli_9deebb5d",
        "client_name": "Alice Cooper",
        "venue_address": "San Jose Hall A",
        "start_date": "2026-08-01",
        "end_date": "2026-08-03",
        "status": "Completed",
        "design_layout_url": "",
        "items_booked": "{\"inv_d150ab75\": 3}",
        "total_invoice_amount": 1080.0,
        "amount_paid": 1080.0,
        "remaining_balance": 0.0,
        "crew_assignments": "[{\"worker_id\": \"usr_labor_1\", \"name\": \"Marcus Chen\", \"pay_rate\": 150.0, \"paid\": false}]",
        "max_workforce_capacity": 4,
        "notes": "Testing auto receipt calculations",
        "id": "evt_8146b0c5"
    },
    {
        "client_id": "cli_9deebb5d",
        "client_name": "Alice Cooper",
        "venue_address": "San Jose Hall A",
        "start_date": "2026-08-02",
        "end_date": "2026-08-04",
        "status": "Confirmed",
        "design_layout_url": "",
        "items_booked": "{\"inv_d150ab75\": 3}",
        "total_invoice_amount": 1080.0,
        "amount_paid": 0.0,
        "remaining_balance": 1080.0,
        "crew_assignments": "[{\"worker_id\": \"usr_labor_1\", \"name\": \"Marcus Chen\", \"pay_rate\": 150.0, \"paid\": false}]",
        "max_workforce_capacity": 4,
        "notes": "Testing auto receipt calculations",
        "id": "evt_572f2f24"
    },
    {
        "client_id": "cli_af6d4606",
        "client_name": "Alice Cooper",
        "venue_address": "San Jose Hall A",
        "start_date": "2026-08-01",
        "end_date": "2026-08-03",
        "status": "Completed",
        "design_layout_url": "",
        "items_booked": "{\"inv_17285317\": 3}",
        "total_invoice_amount": 1080.0,
        "amount_paid": 1080.0,
        "remaining_balance": 0.0,
        "crew_assignments": "[{\"worker_id\": \"usr_labor_1\", \"name\": \"Marcus Chen\", \"pay_rate\": 150.0, \"paid\": false}]",
        "max_workforce_capacity": 4,
        "notes": "Testing auto receipt calculations",
        "id": "evt_3aaf5682"
    },
    {
        "client_id": "cli_af6d4606",
        "client_name": "Alice Cooper",
        "venue_address": "San Jose Hall A",
        "start_date": "2026-08-02",
        "end_date": "2026-08-04",
        "status": "Confirmed",
        "design_layout_url": "",
        "items_booked": "{\"inv_17285317\": 3}",
        "total_invoice_amount": 1080.0,
        "amount_paid": 0.0,
        "remaining_balance": 1080.0,
        "crew_assignments": "[{\"worker_id\": \"usr_labor_1\", \"name\": \"Marcus Chen\", \"pay_rate\": 150.0, \"paid\": false}]",
        "max_workforce_capacity": 4,
        "notes": "Testing auto receipt calculations",
        "id": "evt_ab32ccc3"
    },
    {
        "client_id": "cli_a1c7dc1a",
        "client_name": "Alice Cooper",
        "venue_address": "San Jose Hall A",
        "start_date": "2026-08-01",
        "end_date": "2026-08-03",
        "status": "Completed",
        "design_layout_url": "",
        "items_booked": "{\"inv_21e74ae9\": 3}",
        "total_invoice_amount": 1080.0,
        "amount_paid": 1080.0,
        "remaining_balance": 0.0,
        "crew_assignments": "[{\"worker_id\": \"usr_labor_1\", \"name\": \"Marcus Chen\", \"pay_rate\": 150.0, \"paid\": false}]",
        "payment_history": "[{\"amount\": 1080.0, \"payment_method\": \"Cash\", \"received_at\": \"2026-06-19T02:42:27.072970Z\"}]",
        "max_workforce_capacity": 4,
        "notes": "Updated after deposit",
        "id": "evt_f9d1696b"
    },
    {
        "client_id": "cli_a1c7dc1a",
        "client_name": "Alice Cooper",
        "venue_address": "San Jose Hall A",
        "start_date": "2026-08-02",
        "end_date": "2026-08-04",
        "status": "Confirmed",
        "design_layout_url": "",
        "items_booked": "{\"inv_21e74ae9\": 3}",
        "total_invoice_amount": 1080.0,
        "amount_paid": 0.0,
        "remaining_balance": 1080.0,
        "crew_assignments": "[{\"worker_id\": \"usr_labor_1\", \"name\": \"Marcus Chen\", \"pay_rate\": 150.0, \"paid\": false}]",
        "payment_history": "[]",
        "max_workforce_capacity": 4,
        "notes": "Testing auto receipt calculations",
        "id": "evt_4a59bfb3"
    },
    {
        "client_id": "cli_d5c5e3f9",
        "client_name": "Alice Cooper",
        "venue_address": "San Jose Hall A",
        "start_date": "2026-08-01",
        "end_date": "2026-08-03",
        "status": "Completed",
        "design_layout_url": "",
        "items_booked": "{\"inv_927e6c0d\": 3}",
        "total_invoice_amount": 1080.0,
        "amount_paid": 1080.0,
        "remaining_balance": 0.0,
        "crew_assignments": "[{\"worker_id\": \"usr_labor_1\", \"name\": \"Marcus Chen\", \"pay_rate\": 150.0, \"paid\": false}]",
        "payment_history": "[{\"amount\": 1080.0, \"payment_method\": \"Cash\", \"received_at\": \"2026-06-19T02:43:46.994315Z\"}]",
        "max_workforce_capacity": 4,
        "notes": "Updated after deposit",
        "id": "evt_3de9d034"
    },
    {
        "client_id": "cli_d5c5e3f9",
        "client_name": "Alice Cooper",
        "venue_address": "San Jose Hall A",
        "start_date": "2026-08-02",
        "end_date": "2026-08-04",
        "status": "Confirmed",
        "design_layout_url": "",
        "items_booked": "{\"inv_927e6c0d\": 3}",
        "total_invoice_amount": 1080.0,
        "amount_paid": 0.0,
        "remaining_balance": 1080.0,
        "crew_assignments": "[{\"worker_id\": \"usr_labor_1\", \"name\": \"Marcus Chen\", \"pay_rate\": 150.0, \"paid\": false}]",
        "payment_history": "[]",
        "max_workforce_capacity": 4,
        "notes": "Testing auto receipt calculations",
        "id": "evt_2cf48c6c"
    },
    {
        "client_id": "cli_8b816dcc",
        "client_name": "Alice Cooper",
        "venue_address": "San Jose Hall A",
        "start_date": "2026-08-01",
        "end_date": "2026-08-03",
        "status": "Completed",
        "design_layout_url": "",
        "items_booked": "{\"inv_fdcae7ca\": 3}",
        "total_invoice_amount": 1080.0,
        "amount_paid": 1080.0,
        "remaining_balance": 0.0,
        "crew_assignments": "[{\"worker_id\": \"usr_labor_1\", \"name\": \"Marcus Chen\", \"pay_rate\": 150.0, \"paid\": false}]",
        "payment_history": "[{\"amount\": 1080.0, \"payment_method\": \"Cash\", \"received_at\": \"2026-06-19T03:33:49.299662Z\"}]",
        "max_workforce_capacity": 4,
        "notes": "Updated after deposit",
        "id": "evt_baadd7e3"
    },
    {
        "client_id": "cli_8b816dcc",
        "client_name": "Alice Cooper",
        "venue_address": "San Jose Hall A",
        "start_date": "2026-08-02",
        "end_date": "2026-08-04",
        "status": "Confirmed",
        "design_layout_url": "",
        "items_booked": "{\"inv_fdcae7ca\": 3}",
        "total_invoice_amount": 1080.0,
        "amount_paid": 0.0,
        "remaining_balance": 1080.0,
        "crew_assignments": "[{\"worker_id\": \"usr_labor_1\", \"name\": \"Marcus Chen\", \"pay_rate\": 150.0, \"paid\": false}]",
        "payment_history": "[]",
        "max_workforce_capacity": 4,
        "notes": "Testing auto receipt calculations",
        "id": "evt_374e7a87"
    },
    {
        "client_id": "cli_31eaa363",
        "client_name": "Alice Cooper",
        "venue_address": "San Jose Hall A",
        "start_date": "2026-08-01",
        "end_date": "2026-08-03",
        "status": "Completed",
        "design_layout_url": "",
        "items_booked": "{\"inv_7b7ead6a\": 3}",
        "total_invoice_amount": 1080.0,
        "amount_paid": 1080.0,
        "remaining_balance": 0.0,
        "crew_assignments": "[{\"worker_id\": \"usr_labor_1\", \"name\": \"Marcus Chen\", \"pay_rate\": 150.0, \"paid\": false}]",
        "payment_history": "[{\"amount\": 1080.0, \"payment_method\": \"Cash\", \"received_at\": \"2026-06-19T03:37:16.051964Z\"}]",
        "max_workforce_capacity": 4,
        "notes": "Updated after deposit",
        "id": "evt_80c88bb1"
    },
    {
        "client_id": "cli_31eaa363",
        "client_name": "Alice Cooper",
        "venue_address": "San Jose Hall A",
        "start_date": "2026-08-02",
        "end_date": "2026-08-04",
        "status": "Confirmed",
        "design_layout_url": "",
        "items_booked": "{\"inv_7b7ead6a\": 3}",
        "total_invoice_amount": 1080.0,
        "amount_paid": 0.0,
        "remaining_balance": 1080.0,
        "crew_assignments": "[{\"worker_id\": \"usr_labor_1\", \"name\": \"Marcus Chen\", \"pay_rate\": 150.0, \"paid\": false}]",
        "payment_history": "[]",
        "max_workforce_capacity": 4,
        "notes": "Testing auto receipt calculations",
        "id": "evt_e164b7b1"
    },
    {
        "client_id": "cli_9f91b219",
        "client_name": "Alice Cooper",
        "venue_address": "San Jose Hall A",
        "start_date": "2026-08-01",
        "end_date": "2026-08-03",
        "status": "Completed",
        "design_layout_url": "",
        "items_booked": "{\"inv_4c3e5a12\": 3}",
        "total_invoice_amount": 1080.0,
        "amount_paid": 1080.0,
        "remaining_balance": 0.0,
        "crew_assignments": "[{\"worker_id\": \"usr_labor_1\", \"name\": \"Marcus Chen\", \"pay_rate\": 150.0, \"paid\": false}]",
        "payment_history": "[{\"amount\": 1080.0, \"payment_method\": \"Cash\", \"received_at\": \"2026-06-19T03:39:49.993312Z\"}]",
        "max_workforce_capacity": 4,
        "notes": "Updated after deposit",
        "id": "evt_a4360798"
    },
    {
        "client_id": "cli_9f91b219",
        "client_name": "Alice Cooper",
        "venue_address": "San Jose Hall A",
        "start_date": "2026-08-02",
        "end_date": "2026-08-04",
        "status": "Confirmed",
        "design_layout_url": "",
        "items_booked": "{\"inv_4c3e5a12\": 3}",
        "total_invoice_amount": 1080.0,
        "amount_paid": 0.0,
        "remaining_balance": 1080.0,
        "crew_assignments": "[{\"worker_id\": \"usr_labor_1\", \"name\": \"Marcus Chen\", \"pay_rate\": 150.0, \"paid\": false}]",
        "payment_history": "[]",
        "max_workforce_capacity": 4,
        "notes": "Testing auto receipt calculations",
        "id": "evt_4cb3e416"
    },
    {
        "client_id": "cli_3a9ffa67",
        "client_name": "Alice Cooper",
        "venue_address": "San Jose Hall A",
        "start_date": "2026-08-01",
        "end_date": "2026-08-03",
        "status": "Completed",
        "design_layout_url": "",
        "items_booked": "{\"inv_8de69452\": 3}",
        "total_invoice_amount": 1080.0,
        "amount_paid": 1080.0,
        "remaining_balance": 0.0,
        "crew_assignments": "[{\"worker_id\": \"usr_labor_1\", \"name\": \"Marcus Chen\", \"pay_rate\": 150.0, \"paid\": false}]",
        "payment_history": "[{\"amount\": 1080.0, \"payment_method\": \"Cash\", \"received_at\": \"2026-06-19T03:42:58.758915Z\"}]",
        "max_workforce_capacity": 4,
        "notes": "Updated after deposit",
        "id": "evt_39e8b496"
    },
    {
        "client_id": "cli_3a9ffa67",
        "client_name": "Alice Cooper",
        "venue_address": "San Jose Hall A",
        "start_date": "2026-08-02",
        "end_date": "2026-08-04",
        "status": "Confirmed",
        "design_layout_url": "",
        "items_booked": "{\"inv_8de69452\": 3}",
        "total_invoice_amount": 1080.0,
        "amount_paid": 0.0,
        "remaining_balance": 1080.0,
        "crew_assignments": "[{\"worker_id\": \"usr_labor_1\", \"name\": \"Marcus Chen\", \"pay_rate\": 150.0, \"paid\": false}]",
        "payment_history": "[]",
        "max_workforce_capacity": 4,
        "notes": "Testing auto receipt calculations",
        "id": "evt_47b5f976"
    },
    {
        "client_id": "cli_bffd23a2",
        "client_name": "Alice Cooper",
        "venue_address": "San Jose Hall A",
        "start_date": "2026-08-01",
        "end_date": "2026-08-03",
        "status": "Completed",
        "design_layout_url": "",
        "items_booked": "{\"inv_ec640ddd\": 3}",
        "total_invoice_amount": 1080.0,
        "amount_paid": 1080.0,
        "remaining_balance": 0.0,
        "crew_assignments": "[{\"worker_id\": \"usr_labor_1\", \"name\": \"Marcus Chen\", \"pay_rate\": 150.0, \"paid\": false}]",
        "payment_history": "[{\"amount\": 1080.0, \"payment_method\": \"Cash\", \"received_at\": \"2026-06-19T04:21:44.561337Z\"}]",
        "max_workforce_capacity": 4,
        "notes": "Updated after deposit",
        "id": "evt_e5af995f"
    },
    {
        "client_id": "cli_bffd23a2",
        "client_name": "Alice Cooper",
        "venue_address": "San Jose Hall A",
        "start_date": "2026-08-02",
        "end_date": "2026-08-04",
        "status": "Confirmed",
        "design_layout_url": "",
        "items_booked": "{\"inv_ec640ddd\": 3}",
        "total_invoice_amount": 1080.0,
        "amount_paid": 0.0,
        "remaining_balance": 1080.0,
        "crew_assignments": "[{\"worker_id\": \"usr_labor_1\", \"name\": \"Marcus Chen\", \"pay_rate\": 150.0, \"paid\": false}]",
        "payment_history": "[]",
        "max_workforce_capacity": 4,
        "notes": "Testing auto receipt calculations",
        "id": "evt_b8768f39"
    },
    {
        "client_id": "cli_44cb8a2f",
        "client_name": "Alice Cooper",
        "venue_address": "San Jose Hall A",
        "start_date": "2026-08-01",
        "end_date": "2026-08-03",
        "status": "Completed",
        "design_layout_url": "",
        "items_booked": "{\"inv_cff13082\": 3}",
        "total_invoice_amount": 1080.0,
        "amount_paid": 1080.0,
        "remaining_balance": 0.0,
        "crew_assignments": "[{\"worker_id\": \"usr_labor_1\", \"name\": \"Marcus Chen\", \"pay_rate\": 150.0, \"paid\": false}]",
        "payment_history": "[{\"amount\": 1080.0, \"payment_method\": \"Cash\", \"received_at\": \"2026-06-19T04:28:49.011364Z\"}]",
        "max_workforce_capacity": 4,
        "notes": "Updated after deposit",
        "id": "evt_8b76fe93"
    },
    {
        "client_id": "cli_44cb8a2f",
        "client_name": "Alice Cooper",
        "venue_address": "San Jose Hall A",
        "start_date": "2026-08-02",
        "end_date": "2026-08-04",
        "status": "Confirmed",
        "design_layout_url": "",
        "items_booked": "{\"inv_cff13082\": 3}",
        "total_invoice_amount": 1080.0,
        "amount_paid": 0.0,
        "remaining_balance": 1080.0,
        "crew_assignments": "[{\"worker_id\": \"usr_labor_1\", \"name\": \"Marcus Chen\", \"pay_rate\": 150.0, \"paid\": false}]",
        "payment_history": "[]",
        "max_workforce_capacity": 4,
        "notes": "Testing auto receipt calculations",
        "id": "evt_bc57e2f1"
    },
    {
        "client_id": "cli_6630b0f6",
        "client_name": "Alice Cooper",
        "venue_address": "San Jose Hall A",
        "start_date": "2026-08-01",
        "end_date": "2026-08-03",
        "status": "Completed",
        "design_layout_url": "",
        "items_booked": "{\"inv_256e507d\": 3}",
        "total_invoice_amount": 1080.0,
        "amount_paid": 1080.0,
        "remaining_balance": 0.0,
        "crew_assignments": "[{\"worker_id\": \"usr_labor_1\", \"name\": \"Marcus Chen\", \"pay_rate\": 150.0, \"paid\": false}]",
        "payment_history": "[{\"amount\": 1080.0, \"payment_method\": \"Cash\", \"received_at\": \"2026-06-19T04:29:54.153139Z\"}]",
        "max_workforce_capacity": 4,
        "notes": "Updated after deposit",
        "id": "evt_e255ed70"
    },
    {
        "client_id": "cli_6630b0f6",
        "client_name": "Alice Cooper",
        "venue_address": "San Jose Hall A",
        "start_date": "2026-08-02",
        "end_date": "2026-08-04",
        "status": "Confirmed",
        "design_layout_url": "",
        "items_booked": "{\"inv_256e507d\": 3}",
        "total_invoice_amount": 1080.0,
        "amount_paid": 0.0,
        "remaining_balance": 1080.0,
        "crew_assignments": "[{\"worker_id\": \"usr_labor_1\", \"name\": \"Marcus Chen\", \"pay_rate\": 150.0, \"paid\": false}]",
        "payment_history": "[]",
        "max_workforce_capacity": 4,
        "notes": "Testing auto receipt calculations",
        "id": "evt_c3ce77fe"
    },
    {
        "client_id": "cli_8dacad19",
        "client_name": "Alice Cooper",
        "venue_address": "San Jose Hall A",
        "start_date": "2026-08-01",
        "end_date": "2026-08-03",
        "status": "Completed",
        "design_layout_url": "",
        "items_booked": "{\"inv_1a6b9727\": 3}",
        "total_invoice_amount": 1080.0,
        "amount_paid": 1080.0,
        "remaining_balance": 0.0,
        "crew_assignments": "[{\"worker_id\": \"usr_labor_1\", \"name\": \"Marcus Chen\", \"pay_rate\": 150.0, \"paid\": false}]",
        "payment_history": "[{\"amount\": 1080.0, \"payment_method\": \"Cash\", \"received_at\": \"2026-06-19T04:35:42.949142Z\"}]",
        "max_workforce_capacity": 4,
        "notes": "Updated after deposit",
        "id": "evt_ae22e575"
    },
    {
        "client_id": "cli_8dacad19",
        "client_name": "Alice Cooper",
        "venue_address": "San Jose Hall A",
        "start_date": "2026-08-02",
        "end_date": "2026-08-04",
        "status": "Confirmed",
        "design_layout_url": "",
        "items_booked": "{\"inv_1a6b9727\": 3}",
        "total_invoice_amount": 1080.0,
        "amount_paid": 0.0,
        "remaining_balance": 1080.0,
        "crew_assignments": "[{\"worker_id\": \"usr_labor_1\", \"name\": \"Marcus Chen\", \"pay_rate\": 150.0, \"paid\": false}]",
        "payment_history": "[]",
        "max_workforce_capacity": 4,
        "notes": "Testing auto receipt calculations",
        "id": "evt_6e140bd4"
    },
    {
        "client_id": "cli_e3224247",
        "client_name": "Alice Cooper",
        "venue_address": "San Jose Hall A",
        "start_date": "2026-08-01",
        "end_date": "2026-08-03",
        "status": "Completed",
        "design_layout_url": "",
        "items_booked": "{\"inv_3adf1fd7\": 3}",
        "total_invoice_amount": 1080.0,
        "amount_paid": 1080.0,
        "remaining_balance": 0.0,
        "crew_assignments": "[{\"worker_id\": \"usr_labor_1\", \"name\": \"Marcus Chen\", \"pay_rate\": 150.0, \"paid\": false}]",
        "payment_history": "[{\"amount\": 1080.0, \"payment_method\": \"Cash\", \"received_at\": \"2026-06-19T05:15:14.946051Z\"}]",
        "max_workforce_capacity": 4,
        "notes": "Updated after deposit",
        "id": "evt_5b260313"
    },
    {
        "client_id": "cli_e3224247",
        "client_name": "Alice Cooper",
        "venue_address": "San Jose Hall A",
        "start_date": "2026-08-02",
        "end_date": "2026-08-04",
        "status": "Confirmed",
        "design_layout_url": "",
        "items_booked": "{\"inv_3adf1fd7\": 3}",
        "total_invoice_amount": 1080.0,
        "amount_paid": 0.0,
        "remaining_balance": 1080.0,
        "crew_assignments": "[{\"worker_id\": \"usr_labor_1\", \"name\": \"Marcus Chen\", \"pay_rate\": 150.0, \"paid\": false}]",
        "payment_history": "[]",
        "max_workforce_capacity": 4,
        "notes": "Testing auto receipt calculations",
        "id": "evt_5317fe7f"
    },
    {
        "client_id": "cli_dff36d78",
        "client_name": "Alice Cooper",
        "venue_address": "San Jose Hall A",
        "start_date": "2026-08-01",
        "end_date": "2026-08-03",
        "status": "Completed",
        "design_layout_url": "",
        "items_booked": "{\"inv_573e424f\": 3}",
        "total_invoice_amount": 1080.0,
        "amount_paid": 1080.0,
        "remaining_balance": 0.0,
        "crew_assignments": "[{\"worker_id\": \"usr_labor_1\", \"name\": \"Marcus Chen\", \"pay_rate\": 150.0, \"paid\": false}]",
        "payment_history": "[{\"amount\": 1080.0, \"payment_method\": \"Cash\", \"received_at\": \"2026-06-19T05:17:31.089866Z\"}]",
        "max_workforce_capacity": 4,
        "notes": "Updated after deposit",
        "id": "evt_d894b038"
    },
    {
        "client_id": "cli_dff36d78",
        "client_name": "Alice Cooper",
        "venue_address": "San Jose Hall A",
        "start_date": "2026-08-02",
        "end_date": "2026-08-04",
        "status": "Confirmed",
        "design_layout_url": "",
        "items_booked": "{\"inv_573e424f\": 3}",
        "total_invoice_amount": 1080.0,
        "amount_paid": 0.0,
        "remaining_balance": 1080.0,
        "crew_assignments": "[{\"worker_id\": \"usr_labor_1\", \"name\": \"Marcus Chen\", \"pay_rate\": 150.0, \"paid\": false}]",
        "payment_history": "[]",
        "max_workforce_capacity": 4,
        "notes": "Testing auto receipt calculations",
        "id": "evt_09d66d6c"
    },
    {
        "client_id": "cli_21ac70e9",
        "client_name": "Alice Cooper",
        "venue_address": "San Jose Hall A",
        "start_date": "2026-08-01",
        "end_date": "2026-08-03",
        "status": "Completed",
        "design_layout_url": "",
        "items_booked": "{\"inv_cf987022\": 3}",
        "total_invoice_amount": 1080.0,
        "amount_paid": 1080.0,
        "remaining_balance": 0.0,
        "crew_assignments": "[{\"worker_id\": \"usr_labor_1\", \"name\": \"Marcus Chen\", \"pay_rate\": 150.0, \"paid\": false}]",
        "payment_history": "[{\"amount\": 1080.0, \"payment_method\": \"Cash\", \"received_at\": \"2026-06-19T05:18:49.480951Z\"}]",
        "max_workforce_capacity": 4,
        "notes": "Updated after deposit",
        "id": "evt_702a72d1"
    },
    {
        "client_id": "cli_21ac70e9",
        "client_name": "Alice Cooper",
        "venue_address": "San Jose Hall A",
        "start_date": "2026-08-02",
        "end_date": "2026-08-04",
        "status": "Confirmed",
        "design_layout_url": "",
        "items_booked": "{\"inv_cf987022\": 3}",
        "total_invoice_amount": 1080.0,
        "amount_paid": 0.0,
        "remaining_balance": 1080.0,
        "crew_assignments": "[{\"worker_id\": \"usr_labor_1\", \"name\": \"Marcus Chen\", \"pay_rate\": 150.0, \"paid\": false}]",
        "payment_history": "[]",
        "max_workforce_capacity": 4,
        "notes": "Testing auto receipt calculations",
        "id": "evt_3156ff01"
    },
    {
        "client_id": "cli_dfa69569",
        "client_name": "Alice Cooper",
        "venue_address": "San Jose Hall A",
        "start_date": "2026-08-01",
        "end_date": "2026-08-03",
        "status": "Completed",
        "design_layout_url": "",
        "items_booked": "{\"inv_12f06e04\": 3}",
        "total_invoice_amount": 1080.0,
        "amount_paid": 1080.0,
        "remaining_balance": 0.0,
        "crew_assignments": "[{\"worker_id\": \"usr_labor_1\", \"name\": \"Marcus Chen\", \"pay_rate\": 150.0, \"paid\": false}]",
        "payment_history": "[{\"amount\": 1080.0, \"payment_method\": \"Cash\", \"received_at\": \"2026-06-19T05:19:25.501063Z\"}]",
        "max_workforce_capacity": 4,
        "notes": "Updated after deposit",
        "id": "evt_5f5d7201"
    },
    {
        "client_id": "cli_dfa69569",
        "client_name": "Alice Cooper",
        "venue_address": "San Jose Hall A",
        "start_date": "2026-08-02",
        "end_date": "2026-08-04",
        "status": "Confirmed",
        "design_layout_url": "",
        "items_booked": "{\"inv_12f06e04\": 3}",
        "total_invoice_amount": 1080.0,
        "amount_paid": 0.0,
        "remaining_balance": 1080.0,
        "crew_assignments": "[{\"worker_id\": \"usr_labor_1\", \"name\": \"Marcus Chen\", \"pay_rate\": 150.0, \"paid\": false}]",
        "payment_history": "[]",
        "max_workforce_capacity": 4,
        "notes": "Testing auto receipt calculations",
        "id": "evt_abaf67a7"
    },
    {
        "client_id": "cli_8e9d1229",
        "client_name": "Alice Cooper",
        "venue_address": "San Jose Hall A",
        "start_date": "2026-08-01",
        "end_date": "2026-08-03",
        "status": "Completed",
        "design_layout_url": "",
        "items_booked": "{\"inv_c5fcab19\": 3}",
        "total_invoice_amount": 1080.0,
        "amount_paid": 1080.0,
        "remaining_balance": 0.0,
        "crew_assignments": "[{\"worker_id\": \"usr_labor_1\", \"name\": \"Marcus Chen\", \"pay_rate\": 150.0, \"paid\": false}]",
        "payment_history": "[{\"amount\": 1080.0, \"payment_method\": \"Cash\", \"received_at\": \"2026-06-19T05:20:09.635008Z\"}]",
        "max_workforce_capacity": 4,
        "notes": "Updated after deposit",
        "id": "evt_64a39ac2"
    },
    {
        "client_id": "cli_8e9d1229",
        "client_name": "Alice Cooper",
        "venue_address": "San Jose Hall A",
        "start_date": "2026-08-02",
        "end_date": "2026-08-04",
        "status": "Confirmed",
        "design_layout_url": "",
        "items_booked": "{\"inv_c5fcab19\": 3}",
        "total_invoice_amount": 1080.0,
        "amount_paid": 0.0,
        "remaining_balance": 1080.0,
        "crew_assignments": "[{\"worker_id\": \"usr_labor_1\", \"name\": \"Marcus Chen\", \"pay_rate\": 150.0, \"paid\": false}]",
        "payment_history": "[]",
        "max_workforce_capacity": 4,
        "notes": "Testing auto receipt calculations",
        "id": "evt_a76c4ed2"
    },
    {
        "client_id": "cli_b62dda24",
        "client_name": "Alice Cooper",
        "venue_address": "San Jose Hall A",
        "start_date": "2026-08-01",
        "end_date": "2026-08-03",
        "status": "Completed",
        "design_layout_url": "",
        "items_booked": "{\"inv_12ac1020\": 3}",
        "total_invoice_amount": 1080.0,
        "amount_paid": 1080.0,
        "remaining_balance": 0.0,
        "crew_assignments": "[{\"worker_id\": \"usr_labor_1\", \"name\": \"Marcus Chen\", \"pay_rate\": 150.0, \"paid\": false}]",
        "payment_history": "[{\"amount\": 1080.0, \"payment_method\": \"Cash\", \"received_at\": \"2026-06-19T05:41:02.292808Z\"}]",
        "max_workforce_capacity": 4,
        "notes": "Updated after deposit",
        "id": "evt_2554729b"
    },
    {
        "client_id": "cli_b62dda24",
        "client_name": "Alice Cooper",
        "venue_address": "San Jose Hall A",
        "start_date": "2026-08-02",
        "end_date": "2026-08-04",
        "status": "Confirmed",
        "design_layout_url": "",
        "items_booked": "{\"inv_12ac1020\": 3}",
        "total_invoice_amount": 1080.0,
        "amount_paid": 0.0,
        "remaining_balance": 1080.0,
        "crew_assignments": "[{\"worker_id\": \"usr_labor_1\", \"name\": \"Marcus Chen\", \"pay_rate\": 150.0, \"paid\": false}]",
        "payment_history": "[]",
        "max_workforce_capacity": 4,
        "notes": "Testing auto receipt calculations",
        "id": "evt_37746ab5"
    }
]